latex_trim/latex_trim.py
latex_trim-0.1.3.dist-info/entry_points.txt
latex_trim-0.1.3.dist-info/LICENSE
latex_trim-0.1.3.dist-info/WHEEL
latex_trim-0.1.3.dist-info/METADATA
latex_trim-0.1.3.dist-info/RECORD
